[
    {
        "base_url": "http://mirror.centos.org/centos/8-stream/AppStream/x86_64/os/"
    },
    {
        "base_url": "http://mirror.centos.org/centos/8-stream/BaseOS/x86_64/os/"
    },
    {
        "base_url": "http://mirror.centos.org/centos/8-stream/extras/x86_64/os/"
    },
    {
        "base_url": "http://mirror.stream.centos.org/9-stream/AppStream/x86_64/os/"
    },
    {
        "base_url": "http://mirror.stream.centos.org/9-stream/BaseOS/x86_64/os/"
    },
    {
        "base_url": "https://cdn.redhat.com/content/dist/layered/rhel8/x86_64/ansible/2/os"
    },
    {
        "base_url": "https://cdn.redhat.com/content/dist/layered/rhel8/x86_64/ansible/2/os"
    },
    {
        "base_url": "https://cdn.redhat.com/content/dist/rhel8/8.4/x86_64/appstream/os"
    },
    {
        "base_url": "https://cdn.redhat.com/content/dist/rhel8/8.4/x86_64/baseos/os"
    },
    {
        "base_url": "https://cdn.redhat.com/content/dist/rhel8/8.5/x86_64/appstream/os"
    },
    {
        "base_url": "https://cdn.redhat.com/content/dist/rhel8/8.5/x86_64/baseos/os"
    },
    {
        "base_url": "https://cdn.redhat.com/content/dist/rhel8/8.6/x86_64/appstream/os"
    },
    {
        "base_url": "https://cdn.redhat.com/content/dist/rhel8/8.6/x86_64/baseos/os"
    },
    {
        "base_url": "https://cdn.redhat.com/content/dist/rhel9/9.0/x86_64/appstream/os"
    },
    {
        "base_url": "https://cdn.redhat.com/content/dist/rhel9/9.0/x86_64/baseos/os"
    },
    {
        "base_url": "https://packages.cloud.google.com/yum/repos/cloud-sdk-el8-x86_64"
    },
    {
        "base_url": "https://packages.cloud.google.com/yum/repos/cloud-sdk-el8-x86_64"
    },
    {
        "base_url": "https://packages.cloud.google.com/yum/repos/cloud-sdk-el8-x86_64"
    },
    {
        "base_url": "https://packages.cloud.google.com/yum/repos/cloud-sdk-el8-x86_64"
    },
    {
        "base_url": "https://packages.cloud.google.com/yum/repos/cloud-sdk-el9-x86_64"
    },
    {
        "base_url": "https://packages.cloud.google.com/yum/repos/cloud-sdk-el9-x86_64"
    },
    {
        "base_url": "https://packages.cloud.google.com/yum/repos/google-compute-engine-el8-x86_64-stable"
    },
    {
        "base_url": "https://packages.cloud.google.com/yum/repos/google-compute-engine-el8-x86_64-stable"
    },
    {
        "base_url": "https://packages.cloud.google.com/yum/repos/google-compute-engine-el8-x86_64-stable"
    },
    {
        "base_url": "https://packages.cloud.google.com/yum/repos/google-compute-engine-el8-x86_64-stable"
    },
    {
        "base_url": "https://packages.cloud.google.com/yum/repos/google-compute-engine-el9-x86_64-stable"
    },
    {
        "base_url": "https://packages.cloud.google.com/yum/repos/google-compute-engine-el9-x86_64-stable"
    }
]
